txAMQP-0.7.0.dist-info/DESCRIPTION.rst
txAMQP-0.7.0.dist-info/METADATA
txAMQP-0.7.0.dist-info/RECORD
txAMQP-0.7.0.dist-info/WHEEL
txAMQP-0.7.0.dist-info/metadata.json
txAMQP-0.7.0.dist-info/top_level.txt
txamqp/__init__.py
txamqp/client.py
txamqp/codec.py
txamqp/connection.py
txamqp/content.py
txamqp/delegate.py
txamqp/endpoint.py
txamqp/factory.py
txamqp/message.py
txamqp/protocol.py
txamqp/queue.py
txamqp/spec.py
txamqp/testing.py
txamqp/testlib.py
txamqp/xmlutil.py
txamqp/contrib/__init__.py
txamqp/contrib/thrift/__init__.py
txamqp/contrib/thrift/client.py
txamqp/contrib/thrift/protocol.py
txamqp/contrib/thrift/service.py
txamqp/contrib/thrift/transport.py
txamqp/test/__init__.py
txamqp/test/test_basic.py
txamqp/test/test_broker.py
txamqp/test/test_endpoint.py
txamqp/test/test_event.py
txamqp/test/test_example.py
txamqp/test/test_exchange.py
txamqp/test/test_factory.py
txamqp/test/test_heartbeat.py
txamqp/test/test_protocol.py
txamqp/test/test_queue.py
txamqp/test/test_testing.py
txamqp/test/test_testlib.py
txamqp/test/test_tx.py
