Metadata-Version: 2.0
Name: txAMQP
Version: 0.7.0
Summary: Python library for communicating with AMQP peers and brokers using Twisted
Home-page: https://launchpad.net/txamqp
Author: Esteve Fernandez
Author-email: esteve@fluidinfo.com
License: UNKNOWN
Platform: UNKNOWN
Requires-Dist: Twisted
